{"0": "Lasagne: Fräs färsen i olivoljan i en stekpanna under omrörning. Krydda med salt, peppar och timjan. Häll upp i en kastrull och tillsätt tomatsåsen och låt sjuda några minuter.", "1": "Koka lasagneplattorna mjuka i saltat vatten i omgångar och låt dem rinna av. ", "2": "Koka upp mjölk och grädde.", "3": "Varva lasagneplattorna med färsen på tallrikar. Mixa parmesanen i gräddmjölken och häll över lasagnen.", "4": "Sallad: Låt kronärtskockorna rinna av och skär dem i skivor. Skala och skiva löken tunt.  Blanda det med ruccola, vinäger och olivolja. Servera tillsammans med lasagnen."}