{"0": "1 dl torkad svamp t ex trattkantareller", "1": "2 dl vatten", "2": "1 påse fryst quorn i strimlor (à 300 g) eller torkade sojastrimlor (à 125 g)", "3": "1 gul lök", "4": "1 tsk enbär", "5": "1 msk smör", "6": "2 1/2 dl matlagningsgrädde", "7": "1/2 dl portvin", "8": "1 tsk torkad rosmarin eller färsk rosmarin (1 tsk torkad motsvarar 1 msk hackad färsk rosmarin)", "9": "2 tsk svartvinbärsgelé", "10": "1 1/2 msk japansk soja", "11": "1 krm svartpeppar", "12": "ev salt", "13": "ev 1/2 dl hackad bladpersilja till garnering"}